batchx_dev/__init__.py
batchx_dev/cli/__init__.py
batchx_dev/cli/bx_readme.py
batchx_dev/cli/end2end/__init__.py
batchx_dev/cli/end2end/core.py
batchx_dev/cli/end2end/extract.py
batchx_dev/cli/end2end/io.py
batchx_dev/cli/end2end/report.py
batchx_dev/cli/monkeypatch/__init__.py
batchx_dev/cli/monkeypatch/pathlib_monkey_patch.py
batchx_dev/devutils/CTE.py
batchx_dev/devutils/__init__.py
batchx_dev/devutils/debug.py
batchx_dev/devutils/error.py
batchx_dev/devutils/image.py
batchx_dev/devutils/io.py
batchx_dev/devutils/note.py
batchx_dev/devutils/run.py
batchx_dev/toolbox/__init__.py
batchx_dev/toolbox/commandbuilder/__init__.py
batchx_dev/toolbox/commandbuilder/actions.py
batchx_dev/toolbox/commandbuilder/commandbuilder.py
batchx_dev/toolbox/commandbuilder/constraints.py
batchx_dev/toolbox/commandbuilder/kinds.py
batchx_dev/toolbox/improvers/__init__.py
batchx_dev/toolbox/improvers/functiondict_mixin.py
batchx_dev/toolbox/improvers/manifest_improver.py
batchx_dev/toolbox/improvers/readme_improver.py
batchx_dev/toolbox/improvers/guidelines/__init__.py
batchx_dev/toolbox/improvers/guidelines/checks_mixin.py
batchx_dev/toolbox/improvers/guidelines/enrichment_mixin.py
batchx_dev/toolbox/improvers/guidelines/fixes_mixin.py
batchx_dev/toolbox/improvers/renderers/__init__.py
batchx_dev/toolbox/improvers/renderers/renders_mixin.py
batchx_dev/toolbox/improvers/templates/__init__.py
batchx_dev/toolbox/improvers/templates/conditional_count_list.jinja
batchx_dev/toolbox/improvers/templates/context.jinja
batchx_dev/toolbox/improvers/templates/enumeration.jinja
batchx_dev/toolbox/improvers/templates/examples.jinja
batchx_dev/toolbox/improvers/templates/init-readme-pipeline.jinja
batchx_dev/toolbox/improvers/templates/init-readme-tool.jinja
batchx_dev/toolbox/improvers/templates/links.jinja
batchx_dev/toolbox/improvers/templates/parameters.jinja
batchx_dev/toolbox/improvers/templates/pipeline-inputs.jinja
batchx_dev/toolbox/improvers/templates/pipeline-outputs.jinja
batchx_dev-1.0.91.dist-info/METADATA
batchx_dev-1.0.91.dist-info/WHEEL
batchx_dev-1.0.91.dist-info/entry_points.txt
batchx_dev-1.0.91.dist-info/top_level.txt
batchx_dev-1.0.91.dist-info/RECORD
