Metadata-Version: 2.1
Name: batchx-dev
Version: 1.0.91
Summary: BatchX Python developer tools
Home-page: https://github.com/batchx/python-toolbox
Author: Batchx
Author-email: dev@batchx.com
Classifier: Development Status :: 4 - Beta
Classifier: Programming Language :: Python
Requires-Python: >=3.10
Requires-Dist: batchx
Requires-Dist: click
Requires-Dist: jinja2
Requires-Dist: mistletoe
Requires-Dist: boto3
